getsiteinfo/__init__.py
getsiteinfo/awis.py
getsiteinfo-0.1.1.dist-info/DESCRIPTION.rst
getsiteinfo-0.1.1.dist-info/METADATA
getsiteinfo-0.1.1.dist-info/RECORD
getsiteinfo-0.1.1.dist-info/WHEEL
getsiteinfo-0.1.1.dist-info/metadata.json
getsiteinfo-0.1.1.dist-info/top_level.txt
